{
 "based_on": "date",
 "chart_name": "Engineer Wise Visit Report - SRINIVASAN",
 "chart_type": "Count",
 "color": "#a87945",
 "creation": "2022-10-21 12:00:14.069508",
 "docstatus": 0,
 "doctype": "Dashboard Chart",
 "document_type": "Customer Visit",
 "dynamic_filters_json": "[]",
 "filters_json": "[[\"Customer Visit\",\"company\",\"=\",\"ITFD PRODUCTS\",false],[\"Customer Visit\",\"employee\",\"=\",\"HR-EMP-00032\",false]]",
 "group_by_type": "Count",
 "idx": 0,
 "is_public": 1,
 "is_standard": 1,
 "last_synced_on": "2022-10-21 12:00:49.740364",
 "modified": "2022-10-21 12:01:19.883713",
 "modified_by": "Administrator",
 "module": "tekpro",
 "name": "Engineer Wise Visit Report - SRINIVASAN",
 "number_of_groups": 0,
 "owner": "Administrator",
 "source": "",
 "time_interval": "Monthly",
 "timeseries": 1,
 "timespan": "Last Year",
 "type": "Bar",
 "use_report_chart": 0,
 "value_based_on": "",
 "y_axis": []
}